s2protocol/__init__.py
s2protocol/attributes.py
s2protocol/build.py
s2protocol/compat.py
s2protocol/decoders.py
s2protocol/diff.py
s2protocol/encoders.py
s2protocol/namespaces.py
s2protocol/s2_cli.py
s2protocol/versions/__init__.py
s2protocol/versions/protocol15405.py
s2protocol/versions/protocol16561.py
s2protocol/versions/protocol16605.py
s2protocol/versions/protocol16755.py
s2protocol/versions/protocol16939.py
s2protocol/versions/protocol17266.py
s2protocol/versions/protocol17326.py
s2protocol/versions/protocol18092.py
s2protocol/versions/protocol18468.py
s2protocol/versions/protocol18574.py
s2protocol/versions/protocol19132.py
s2protocol/versions/protocol19458.py
s2protocol/versions/protocol19595.py
s2protocol/versions/protocol19679.py
s2protocol/versions/protocol21029.py
s2protocol/versions/protocol22612.py
s2protocol/versions/protocol23260.py
s2protocol/versions/protocol24944.py
s2protocol/versions/protocol26490.py
s2protocol/versions/protocol27950.py
s2protocol/versions/protocol28272.py
s2protocol/versions/protocol28667.py
s2protocol/versions/protocol32283.py
s2protocol/versions/protocol51702.py
s2protocol/versions/protocol52910.py
s2protocol/versions/protocol53644.py
s2protocol/versions/protocol54518.py
s2protocol/versions/protocol55505.py
s2protocol/versions/protocol55958.py
s2protocol/versions/protocol56787.py
s2protocol/versions/protocol57507.py
s2protocol/versions/protocol58400.py
s2protocol/versions/protocol59587.py
s2protocol/versions/protocol60196.py
s2protocol/versions/protocol60321.py
s2protocol/versions/protocol62347.py
s2protocol/versions/protocol62848.py
s2protocol/versions/protocol63454.py
s2protocol/versions/protocol64469.py
s2protocol/versions/protocol65094.py
s2protocol/versions/protocol65384.py
s2protocol/versions/protocol65895.py
s2protocol/versions/protocol66668.py
s2protocol/versions/protocol67188.py
s2protocol/versions/protocol67926.py
s2protocol/versions/protocol69232.py
s2protocol/versions/protocol70154.py
s2protocol-5.0.15.95299.0.dist-info/LICENSE
s2protocol-5.0.15.95299.0.dist-info/METADATA
s2protocol-5.0.15.95299.0.dist-info/WHEEL
s2protocol-5.0.15.95299.0.dist-info/entry_points.txt
s2protocol-5.0.15.95299.0.dist-info/top_level.txt
s2protocol-5.0.15.95299.0.dist-info/RECORD
