Metadata-Version: 2.1
Name: s2protocol
Version: 5.0.15.95299.0
Summary: Python library to decode StarCraft II replay protocols
Home-page: https://github.com/Blizzard/s2protocol
Author: Blizzard Entertainment
Author-email: s2github@blizzard.com
License: UNKNOWN
Platform: UNKNOWN
Classifier: Development Status :: 5 - Production/Stable
Classifier: Environment :: Console
Classifier: Intended Audience :: End Users/Desktop
Classifier: Intended Audience :: Developers
Classifier: License :: OSI Approved :: MIT License
Classifier: Operating System :: POSIX
Classifier: Programming Language :: Python :: 2.6
Classifier: Programming Language :: Python :: 2.7
Classifier: Topic :: Games/Entertainment :: Real Time Strategy
Classifier: Topic :: Software Development :: Libraries
Classifier: Topic :: System :: Archiving
Requires-Dist: mpyq (>=0.2.2)
Provides-Extra: tests
Requires-Dist: tox ; extra == 'tests'
